DjangoWangzhanKaifaCookbook/README.md
DjangoWangzhanKaifaCookbook/__init__.py
DjangoWangzhanKaifaCookbook/__main__.py
DjangoWangzhanKaifaCookbook/file.epub
DjangoWangzhanKaifaCookbook/index.html
DjangoWangzhanKaifaCookbook/css/__init__.py
DjangoWangzhanKaifaCookbook/css/annotations.css
DjangoWangzhanKaifaCookbook/css/main.css
DjangoWangzhanKaifaCookbook/css/normalize.css
DjangoWangzhanKaifaCookbook/css/popup.css
DjangoWangzhanKaifaCookbook/font/__init__.py
DjangoWangzhanKaifaCookbook/font/fontello.eot
DjangoWangzhanKaifaCookbook/font/fontello.svg
DjangoWangzhanKaifaCookbook/font/fontello.ttf
DjangoWangzhanKaifaCookbook/font/fontello.woff
DjangoWangzhanKaifaCookbook/img/__init__.py
DjangoWangzhanKaifaCookbook/img/annotator-glyph-sprite.png
DjangoWangzhanKaifaCookbook/img/annotator-icon-sprite.png
DjangoWangzhanKaifaCookbook/img/apple-touch-icon.png
DjangoWangzhanKaifaCookbook/img/cancelfullscreen.png
DjangoWangzhanKaifaCookbook/img/close.png
DjangoWangzhanKaifaCookbook/img/fullscreen.png
DjangoWangzhanKaifaCookbook/img/loader.gif
DjangoWangzhanKaifaCookbook/img/menu-icon.png
DjangoWangzhanKaifaCookbook/img/save.png
DjangoWangzhanKaifaCookbook/img/saved.png
DjangoWangzhanKaifaCookbook/img/settings-s.png
DjangoWangzhanKaifaCookbook/img/settings.png
DjangoWangzhanKaifaCookbook/img/star.png
DjangoWangzhanKaifaCookbook/js/__init__.py
DjangoWangzhanKaifaCookbook/js/epub.js
DjangoWangzhanKaifaCookbook/js/epub.min.js
DjangoWangzhanKaifaCookbook/js/epub.min.map
DjangoWangzhanKaifaCookbook/js/hooks.min.js
DjangoWangzhanKaifaCookbook/js/hooks.min.map
DjangoWangzhanKaifaCookbook/js/reader.js
DjangoWangzhanKaifaCookbook/js/reader.js.map
DjangoWangzhanKaifaCookbook/js/reader.min.js
DjangoWangzhanKaifaCookbook/js/reader.min.map
DjangoWangzhanKaifaCookbook/js/hooks/__init__.py
DjangoWangzhanKaifaCookbook/js/hooks/extensions/__init__.py
DjangoWangzhanKaifaCookbook/js/hooks/extensions/highlight.js
DjangoWangzhanKaifaCookbook/js/libs/__init__.py
django_wangzhan_kaifa_cookbook-2024.3.1.0.dist-info/METADATA
django_wangzhan_kaifa_cookbook-2024.3.1.0.dist-info/WHEEL
django_wangzhan_kaifa_cookbook-2024.3.1.0.dist-info/entry_points.txt
django_wangzhan_kaifa_cookbook-2024.3.1.0.dist-info/top_level.txt
django_wangzhan_kaifa_cookbook-2024.3.1.0.dist-info/RECORD
